wox/__init__.py
wox-0.0.1.dist-info/METADATA
wox-0.0.1.dist-info/WHEEL
wox-0.0.1.dist-info/RECORD
